nndownload/__init__.py
nndownload/__main__.py
nndownload/ffmpeg_dl.py
nndownload/hls_dl.py
nndownload/nndownload.py
nndownload-1.19.dist-info/LICENSE
nndownload-1.19.dist-info/METADATA
nndownload-1.19.dist-info/WHEEL
nndownload-1.19.dist-info/entry_points.txt
nndownload-1.19.dist-info/top_level.txt
nndownload-1.19.dist-info/RECORD
