Metadata-Version: 2.2
Name: nndownload
Version: 1.19
Summary: nndownload allows you to process videos and other links from Niconico.
Home-page: https://github.com/AlexAplin/nndownload
Author: AlexAplin
Classifier: Programming Language :: Python
Classifier: Programming Language :: Python :: 3
Classifier: License :: OSI Approved :: MIT License
Classifier: Natural Language :: English
Requires-Python: >=3.5.3
License-File: LICENSE
Requires-Dist: aiohttp
Requires-Dist: aiohttp-socks
Requires-Dist: beautifulsoup4
Requires-Dist: ffmpeg-python
Requires-Dist: gevent
Requires-Dist: mutagen
Requires-Dist: pycryptodome
Requires-Dist: requests
Requires-Dist: rich
Requires-Dist: setuptools
Requires-Dist: urllib3
Dynamic: author
Dynamic: classifier
Dynamic: description
Dynamic: description-content-type
Dynamic: home-page
Dynamic: requires-dist
Dynamic: requires-python
Dynamic: summary
